{
  "version": "7",
  "dialect": "postgresql",
  "entries": [
    {
      "idx": 0,
      "version": "7",
      "when": 1771784839409,
      "tag": "0000_icy_phil_sheldon",
      "breakpoints": true
    },
    {
      "idx": 1,
      "version": "7",
      "when": 1771786382903,
      "tag": "0001_fixed_leopardon",
      "breakpoints": true
    },
    {
      "idx": 2,
      "version": "7",
      "when": 1771789651192,
      "tag": "0002_aromatic_quasimodo",
      "breakpoints": true
    },
    {
      "idx": 3,
      "version": "7",
      "when": 1772282323256,
      "tag": "0003_modern_dakota_north",
      "breakpoints": true
    }
  ]
}